simpletools/ServiceQ.py
simpletools/__init__.py
simpletools-0.2.0.dist-info/licenses/LICENSE.txt
simpletools-0.2.0.dist-info/METADATA
simpletools-0.2.0.dist-info/WHEEL
simpletools-0.2.0.dist-info/top_level.txt
simpletools-0.2.0.dist-info/RECORD
