Metadata-Version: 2.4
Name: simpletools
Version: 0.2.0
Summary: simpletools
Author-email: Marcin Rosinski <marcin@getsimpletools.com>
License: BSD-3-Clause
Keywords: amqp,pika,queue
Classifier: Programming Language :: Python :: 3
Classifier: Programming Language :: Python :: 3.6
Classifier: License :: OSI Approved :: BSD License
Classifier: Operating System :: OS Independent
Requires-Python: >=3.6
License-File: LICENSE.txt
Requires-Dist: pika>=1.0.0
Dynamic: license-file
